stix_shifter_modules/datadog/__init__.py
stix_shifter_modules/datadog/entry_point.py
stix_shifter_modules/datadog/configuration/config.json
stix_shifter_modules/datadog/configuration/dialects.json
stix_shifter_modules/datadog/configuration/lang_en.json
stix_shifter_modules/datadog/stix_translation/__init__.py
stix_shifter_modules/datadog/stix_translation/json_to_stix_translator.py
stix_shifter_modules/datadog/stix_translation/query_constructor.py
stix_shifter_modules/datadog/stix_translation/query_translator.py
stix_shifter_modules/datadog/stix_translation/json/events_from_stix_map.json
stix_shifter_modules/datadog/stix_translation/json/operators.json
stix_shifter_modules/datadog/stix_translation/json/processes_from_stix_map.json
stix_shifter_modules/datadog/stix_translation/json/to_stix_map.json
stix_shifter_modules/datadog/stix_transmission/__init__.py
stix_shifter_modules/datadog/stix_transmission/api_client.py
stix_shifter_modules/datadog/stix_transmission/connector.py
stix_shifter_modules/datadog/stix_transmission/error_mapper.py
stix_shifter_modules_datadog-8.0.2.dist-info/licenses/AUTHORS.md
stix_shifter_modules_datadog-8.0.2.dist-info/licenses/LICENSE.md
stix_shifter_modules_datadog-8.0.2.dist-info/licenses/NOTICE
stix_shifter_modules_datadog-8.0.2.dist-info/METADATA
stix_shifter_modules_datadog-8.0.2.dist-info/WHEEL
stix_shifter_modules_datadog-8.0.2.dist-info/top_level.txt
stix_shifter_modules_datadog-8.0.2.dist-info/RECORD
